LICENSE
nbswave/__init__.py
nbswave/audio.py
nbswave/main.py
nbswave/nbs.py
nbswave-0.4.0.dist-info/LICENSE
nbswave-0.4.0.dist-info/METADATA
nbswave-0.4.0.dist-info/WHEEL
nbswave-0.4.0.dist-info/RECORD
