Metadata-Version: 2.1
Name: nbswave
Version: 0.4.0
Summary: An utility to render note block songs to a variety of audio formats
Home-page: https://github.com/Bentroen/nbswave
License: MIT
Keywords: minecraft,note-block-studio,noteblock,nbs,audio
Author: Bentroen
Author-email: bemcdc@gmail.com
Requires-Python: >=3.8,<3.13
Classifier: License :: OSI Approved :: MIT License
Classifier: Programming Language :: Python :: 3
Classifier: Programming Language :: Python :: 3.8
Classifier: Programming Language :: Python :: 3.9
Classifier: Programming Language :: Python :: 3.10
Classifier: Programming Language :: Python :: 3.11
Classifier: Programming Language :: Python :: 3.12
Requires-Dist: numpy (>=1.23.1,<2.0.0)
Requires-Dist: pydub (>=0.25.1,<0.26.0)
Requires-Dist: pynbs (>=1.1.0,<2.0.0)
Project-URL: Repository, https://github.com/Bentroen/nbswave
